{
    "button": {
        "normal_text": {
            "font_path": "../assets/AstolatFont.ttf",
            "font_size": 14,
            "colour": "#FFFFFF"
        },
        "hovered_text": {
            "font_path": "../assets/AstolatFont.ttf",
            "font_size": 14,
            "colour": "#FFFFFF"
        },
        "normal_bg": "#5e7cac",
        "hovered_bg": "#425e87",
        "normal_border": {
            "colour": "#162635",
            "width": 2
        },
        "hovered_border": {
            "colour": "#425e87",
            "width": 2
        },
        "shape_corner_radius": 10
    }
}
